{
  "ATTACK.description": "这个敌人将要[gold]攻击[/gold]{IsMultiplayer:所有人|}造成[blue]{Damage}[/blue]点伤害{Repeat:choose(1):|[blue]{}[/blue]次}。",
  "ATTACK.title": "攻势",
  "BUFF.description": "这个敌人将要使用一个[gold]强化效果[/gold]。",
  "BUFF.title": "强化",
  "CARD_DEBUFF.description": "这个敌人将要对你的卡牌施加[gold]侵蚀[/gold]。",
  "CARD_DEBUFF.title": "恶意",
  "DEATH_BLOW.description": "这个生物试图拉你一起陪葬。它会在被摧毁前攻击你造成[blue]{Damage}[/blue]点伤害。",
  "DEATH_BLOW.title": "濒死一击",
  "DEBUFF.description": "这个敌人将要对你施加一个[gold]负面效果[/gold]。",
  "DEBUFF.title": "策略",
  "DEBUFF_STRONG.description": "这个敌人将要对你施加一个强大的[gold]负面效果[/gold]。",
  "DEBUFF_STRONG.title": "策略",
  "DEFEND.description": "这个敌人将会在其回合获得[gold]格挡[/gold]。",
  "DEFEND.title": "守势",
  "ESCAPE.description": "这个敌人将会[gold]逃跑[/gold]。",
  "ESCAPE.title": "懦弱",
  "FORMAT_DAMAGE_MULTI": "{Damage}[font_size=18]×{Repeat}[/font_size]",
  "FORMAT_DAMAGE_SINGLE": "{Damage}",
  "FORMAT_STATUS_CARD_COUNT": "{CardCount}",
  "HEAL.description": "这个敌人将会[gold]回复[/gold]。",
  "HEAL.title": "回复",
  "SLEEP.description": "这个敌人本回合不会采取任何行动。",
  "SLEEP.title": "沉睡",
  "STATUS.description": "这个敌人将会给你[blue]{CardCount}[/blue]张[gold]状态[/gold]牌。",
  "STATUS.title": "策略",
  "STUN.description": "这个敌人在其下一回合无法行动。",
  "STUN.title": "击晕",
  "SUMMON.description": "这个敌人将要召唤[gold]怪物[/gold]。",
  "SUMMON.title": "召唤",
  "UNKNOWN.description": "这个敌人将要进行某种[gold]未知[/gold]行动。",
  "UNKNOWN.title": "未知"
}
